langchain_teddynote/__init__.py
langchain_teddynote/callbacks.py
langchain_teddynote/evaluator.py
langchain_teddynote/graphs.py
langchain_teddynote/korean.py
langchain_teddynote/logging.py
langchain_teddynote/memory.py
langchain_teddynote/messages.py
langchain_teddynote/models.py
langchain_teddynote/prompts.py
langchain_teddynote/translate.py
langchain_teddynote/community/__init__.py
langchain_teddynote/community/kiwi_tokenizer.py
langchain_teddynote/community/pinecone.py
langchain_teddynote/document_compressors/__init__.py
langchain_teddynote/document_compressors/llm_extractor.py
langchain_teddynote/document_compressors/llm_filter.py
langchain_teddynote/document_loaders/__init__.py
langchain_teddynote/document_loaders/hwp.py
langchain_teddynote/document_parser/__init__.py
langchain_teddynote/document_parser/synapsoft.py
langchain_teddynote/embeddings/__init__.py
langchain_teddynote/embeddings/huggingface.py
langchain_teddynote/retrievers/__init__.py
langchain_teddynote/retrievers/ensemble.py
langchain_teddynote/retrievers/kiwi_bm25.py
langchain_teddynote/tools/__init__.py
langchain_teddynote/tools/news.py
langchain_teddynote/tools/tavily.py
langchain_teddynote/tools/utils.py
langchain_teddynote-0.5.4.dist-info/METADATA
langchain_teddynote-0.5.4.dist-info/WHEEL
langchain_teddynote-0.5.4.dist-info/licenses/LICENSE
langchain_teddynote-0.5.4.dist-info/RECORD
