Metadata-Version: 2.4
Name: langchain-teddynote
Version: 0.5.4
Summary: Helper and utility functions for langchain
Project-URL: Homepage, https://github.com/teddylee777/langchain-teddynote
Project-URL: Repository, https://github.com/teddylee777/langchain-teddynote
Project-URL: Issues, https://github.com/teddylee777/langchain-teddynote/issues
Author-email: Teddy Lee <teddylee777@gmail.com>
License:                                  Apache License
License-File: LICENSE
Classifier: Programming Language :: Python :: 3
Classifier: Programming Language :: Python :: 3.10
Classifier: Programming Language :: Python :: 3.11
Classifier: Programming Language :: Python :: 3.12
Requires-Python: >=3.10
Requires-Dist: anthropic>=0.64.0
Requires-Dist: deepl>=1.22.0
Requires-Dist: feedparser>=6.0.11
Requires-Dist: kiwipiepy>=0.21.0
Requires-Dist: konlpy>=0.6.0
Requires-Dist: langchain-openai>=0.3.30
Requires-Dist: langchain>=0.3.27
Requires-Dist: langgraph>=0.6.5
Requires-Dist: olefile>=0.47
Requires-Dist: openai>=1.99.9
Requires-Dist: pandas>=2.3.1
Requires-Dist: pdf2image>=1.17.0
Requires-Dist: pinecone-client>=6.0.0
Requires-Dist: pinecone-text>=0.11.0
Requires-Dist: python-dotenv>=1.1.1
Requires-Dist: rank-bm25>=0.2.2
Requires-Dist: tavily-python>=0.7.10
Requires-Dist: twine>=6.1.0
